tactile_mnist/__init__.py
tactile_mnist/colormap.py
tactile_mnist/constants.py
tactile_mnist/dataset.py
tactile_mnist/huggingface_dataset.py
tactile_mnist/mesh_dataset.py
tactile_mnist/registration.py
tactile_mnist/tactile_classification_env.py
tactile_mnist/tactile_perception_renderer.py
tactile_mnist/tactile_perception_vector_env.py
tactile_mnist/tactile_pose_estimation_env.py
tactile_mnist/tactile_volume_estimation_env.py
tactile_mnist/touch_data.py
tactile_mnist/util.py
tactile_mnist/resources/__init__.py
tactile_mnist/resources/cycle_gan_tactile_mnist_v0.pth
tactile_mnist/resources/gelsight_mini.mtl
tactile_mnist/resources/gelsight_mini.obj
tactile_mnist/tactile_renderer/__init__.py
tactile_mnist/tactile_renderer/cycle_gan_renderer_torch.py
tactile_mnist/tactile_renderer/cycle_gan_torch.py
tactile_mnist/tactile_renderer/depth_renderer_jax.py
tactile_mnist/tactile_renderer/depth_renderer_numpy.py
tactile_mnist/tactile_renderer/depth_renderer_torch.py
tactile_mnist/tactile_renderer/factory.py
tactile_mnist/tactile_renderer/tactile_renderer.py
tactile_mnist/tactile_renderer/tactile_renderer_jax.py
tactile_mnist/tactile_renderer/tactile_renderer_torch.py
tactile_mnist/tactile_renderer/taxim_renderer_jax.py
tactile_mnist/tactile_renderer/taxim_renderer_torch.py
tactile_mnist-0.11.0.dist-info/licenses/LICENSE
tactile_mnist-0.11.0.dist-info/METADATA
tactile_mnist-0.11.0.dist-info/WHEEL
tactile_mnist-0.11.0.dist-info/top_level.txt
tactile_mnist-0.11.0.dist-info/RECORD
