Metadata-Version: 2.4
Name: tactile-mnist
Version: 0.11.0
Summary: The Tactile MNIST benchmark for active tactile perception.
Author-email: Tim Schneider <tim@robot-learning.de>
License: MIT
Project-URL: Homepage, https://github.com/TimSchneider42/tactile-mnist
License-File: LICENSE
Requires-Dist: ap_gym>=0.3.0
Requires-Dist: filelock
Requires-Dist: numpy
Requires-Dist: transformation3d>=1.0.1
Requires-Dist: tqdm
Requires-Dist: trimesh
Requires-Dist: pyrender
Requires-Dist: scipy
Requires-Dist: requests
Requires-Dist: opencv-python
Requires-Dist: av
Provides-Extra: examples
Requires-Dist: matplotlib; extra == "examples"
Provides-Extra: torch
Requires-Dist: taxim[torch]>=1.4.0; extra == "torch"
Requires-Dist: torch; extra == "torch"
Requires-Dist: torchvision; extra == "torch"
Provides-Extra: jax-cpu
Requires-Dist: taxim[jax-cpu]>=1.4.0; extra == "jax-cpu"
Requires-Dist: jax; extra == "jax-cpu"
Provides-Extra: jax
Requires-Dist: taxim[jax]>=1.4.0; extra == "jax"
Requires-Dist: jax[cuda12]; extra == "jax"
Dynamic: license-file
